zellular/__init__.py
zellular/zellular.py
zellular/networks/__init__.py
zellular/networks/base.py
zellular/networks/eigenlayer.py
zellular/networks/static.py
zellular/networks/types.py
zellular-0.2.10.dist-info/METADATA
zellular-0.2.10.dist-info/WHEEL
zellular-0.2.10.dist-info/top_level.txt
zellular-0.2.10.dist-info/RECORD
