Metadata-Version: 2.4
Name: zellular
Version: 0.2.10
Summary: SDK package for zellular sequencer
Author-email: Mahdi <mahdi@zellular.xyz>
License: MIT
Project-URL: Homepage, https://github.com/zellular-xyz/zellular.py
Keywords: sdk,sequencer,blockchain
Classifier: Programming Language :: Python :: 3
Classifier: License :: OSI Approved :: MIT License
Classifier: Operating System :: OS Independent
Requires-Python: >=3.7.2
Requires-Dist: eigensdk
Requires-Dist: xxhash
Requires-Dist: packaging
Requires-Dist: httpx>=0.24.1
Provides-Extra: dev
Requires-Dist: pytest; extra == "dev"
Requires-Dist: pytest-asyncio; extra == "dev"
Requires-Dist: mypy>=1.0.0; extra == "dev"
Requires-Dist: types-requests; extra == "dev"
Requires-Dist: types-xxhash; extra == "dev"
Requires-Dist: build; extra == "dev"
Requires-Dist: twine; extra == "dev"
